django_pimpmytheme-2.3.dist-info/DESCRIPTION.rst
django_pimpmytheme-2.3.dist-info/METADATA
django_pimpmytheme-2.3.dist-info/RECORD
django_pimpmytheme-2.3.dist-info/WHEEL
django_pimpmytheme-2.3.dist-info/metadata.json
django_pimpmytheme-2.3.dist-info/top_level.txt
pimpmytheme/__init__.py
pimpmytheme/admin.py
pimpmytheme/context_processors.py
pimpmytheme/filters.py
pimpmytheme/folder_management.py
pimpmytheme/models.py
pimpmytheme/static_finder.py
pimpmytheme/template_loader.py
pimpmytheme/tests.py
pimpmytheme/utils.py
pimpmytheme/views.py
pimpmytheme/management/__init__.py
pimpmytheme/management/commands/__init__.py
pimpmytheme/management/commands/create_folders.py
pimpmytheme/management/commands/update_themefolder_from_git.py
pimpmytheme/templatetags/__init__.py
pimpmytheme/templatetags/pimptheme.py
