Metadata-Version: 2.0
Name: django-pimpmytheme
Version: 2.3
Summary: Customise theme (css and template) on a per user/client whatever basis
Home-page: https://github.com/novafloss/django-pimpmytheme
Author: Yohann Gabory
Author-email: novafloss@people-doc.com
License: MIT License
Platform: UNKNOWN
Classifier: Development Status :: 4 - Beta
Classifier: Intended Audience :: Developers
Classifier: License :: OSI Approved :: MIT License
Classifier: Programming Language :: Python
Classifier: Programming Language :: Python :: 2
Classifier: Programming Language :: Python :: 2.7
Classifier: Programming Language :: Python :: 3
Classifier: Programming Language :: Python :: 3.3
Classifier: Programming Language :: Python :: 3.4
Requires-Dist: Django (>=1.8,<1.11)
Requires-Dist: django-compressor (>=2.1.1)
Requires-Dist: gitpython (>1.0.0)
